joca/__init__.py
joca/joca.py
joca-1.4.2.data/data/man/man1/joca.1
joca-1.4.2.data/data/resources/joca.config.json.schema
joca-1.4.2.data/scripts/joca
joca-1.4.2.dist-info/METADATA
joca-1.4.2.dist-info/RECORD
joca-1.4.2.dist-info/WHEEL
joca-1.4.2.dist-info/top_level.txt
joca1/__init__.py
