Metadata-Version: 2.1
Name: joca
Version: 1.4.2
Summary: Sync project lead with ical (for on call assignees)
Home-page: https://www,github.com/betsythefc/joca
Author: Bryce McNab
Author-email: me@brycemcnab.com
License: UNKNOWN
Platform: UNKNOWN
Classifier: Programming Language :: Python :: 2.7
Classifier: Operating System :: OS Independent
Classifier: Development Status :: 5 - Production/Stable
Classifier: License :: OSI Approved :: GNU General Public License v3 (GPLv3)
Classifier: Topic :: Software Development :: Version Control :: Git
Classifier: Environment :: Console
Classifier: Intended Audience :: System Administrators
Classifier: Intended Audience :: Developers
Classifier: Natural Language :: English
Classifier: Topic :: Software Development :: Bug Tracking
Classifier: Topic :: Utilities
Requires-Dist: requests
Requires-Dist: jira
Requires-Dist: icalendar
Requires-Dist: jsonschema
